typefu/__init__.py
typefu/avro.py
typefu/mssql.py
typefu/spark.py
typefu-0.0.2.dist-info/LICENSE
typefu-0.0.2.dist-info/METADATA
typefu-0.0.2.dist-info/WHEEL
typefu-0.0.2.dist-info/top_level.txt
typefu-0.0.2.dist-info/RECORD
