Metadata-Version: 2.1
Name: typefu
Version: 0.0.2
Summary: A type casting guru from your data sources and data formats
Home-page: https://github.com/canimus/typefu
Author: Herminio Vazquez
Author-email: canimus@gmail.com
License: UNKNOWN
Platform: UNKNOWN
Classifier: Programming Language :: Python :: 3
Classifier: License :: OSI Approved :: GNU General Public License v3 (GPLv3)
Classifier: Operating System :: OS Independent
Classifier: Topic :: Utilities
Requires-Python: >=3.6
Requires-Dist: pyspark (>=2.4.4)
